smart_legion_lab_library/__init__.py
smart_legion_lab_library/smart_2fa_secure/__init__.py
smart_legion_lab_library/smart_2fa_secure/core.py
smart_legion_lab_library/smart_2fa_secure/exceptions.py
smart_legion_lab_library/smart_2fa_secure/generators.py
smart_legion_lab_library/smart_2fa_secure/interfaces.py
smart_legion_lab_library/smart_2fa_secure/backends/__init__.py
smart_legion_lab_library/smart_2fa_secure/backends/redis.py
smart_legion_lab_library/smart_2fa_secure/backends/telegram.py
smart_legion_lab_library-1.0.2.dist-info/licenses/LICENSE
smart_legion_lab_library-1.0.2.dist-info/METADATA
smart_legion_lab_library-1.0.2.dist-info/WHEEL
smart_legion_lab_library-1.0.2.dist-info/top_level.txt
smart_legion_lab_library-1.0.2.dist-info/RECORD
